{
  "publicPath": "/client/",
  "all": [
    "index.js",
    "177.js"
  ],
  "initial": [
    "index.js"
  ],
  "async": [
    "177.js"
  ],
  "modules": {
    "7ce8a3cc": [
      0
    ],
    "75afbffc": [
      0
    ],
    "51731e4d": [
      0
    ],
    "7eb02e5e": [
      1
    ],
    "24fdd037": [
      1
    ],
    "1effdeb1": [
      0
    ],
    "7f01958a": [
      0
    ],
    "c36e0360": [
      0
    ],
    "28f264da": [
      0
    ],
    "f64ffb64": [
      0
    ],
    "0c744d0c": [
      0
    ],
    "53ea0e9a": [
      0
    ],
    "0217b13a": [
      0
    ],
    "1929b3d4": [
      0
    ],
    "6fbc4fdc": [
      0
    ],
    "691f1e8a": [
      0
    ],
    "34c750e2": [
      0
    ],
    "130c4394": [
      0
    ],
    "b8250572": [
      0
    ],
    "594d331d": [
      0
    ]
  }
}